web3constant/__init__.py
web3constant/topics.py
web3constant/utility.py
web3constant/Cronos/Dex.py
web3constant/Cronos/ERC20_address.py
web3constant/Cronos/Url.py
web3constant/Cronos/__init__.py
web3constant/Fantom/Dex.py
web3constant/Fantom/ERC20_address.py
web3constant/Fantom/Url.py
web3constant/Fantom/__init__.py
web3_constant-0.0.6.dist-info/LICENSE
web3_constant-0.0.6.dist-info/METADATA
web3_constant-0.0.6.dist-info/WHEEL
web3_constant-0.0.6.dist-info/top_level.txt
web3_constant-0.0.6.dist-info/RECORD
