Metadata-Version: 2.1
Name: web3-constant
Version: 0.0.6
Summary: Useful web3 constant
Home-page: https://github.com/powei-lin/web3-constant
Author: Powei Lin
Author-email: poweilin1994@gmail.com
License: UNKNOWN
Project-URL: Bug Tracker, https://github.com/powei-lin/web3-constant/issues
Platform: UNKNOWN
Classifier: Programming Language :: Python :: 3
Classifier: License :: OSI Approved :: MIT License
Classifier: Operating System :: OS Independent
Requires-Python: >=3.6
License-File: LICENSE
